xfms/__init__.py
xfms/calculations.py
xfms_calculations-0.0.2.dist-info/LICENSE
xfms_calculations-0.0.2.dist-info/METADATA
xfms_calculations-0.0.2.dist-info/WHEEL
xfms_calculations-0.0.2.dist-info/top_level.txt
xfms_calculations-0.0.2.dist-info/RECORD
