Metadata-Version: 2.1
Name: xfms-calculations
Version: 0.0.2
Summary: Perform calculations with ease
Author: Harsha
Author-email: harshanit400@gmail.com
Classifier: Programming Language :: Python :: 3
Classifier: License :: OSI Approved :: MIT License
Classifier: Operating System :: OS Independent
Requires-Python: >=3.6
License-File: LICENSE
